pddb/__init__.py
pddb/pddb.py
pddb/js/pddb.js
pddb/templates/pddb.html
pddb/templates/pddb_table.tpl
pddb-0.3.3.dist-info/DESCRIPTION.rst
pddb-0.3.3.dist-info/METADATA
pddb-0.3.3.dist-info/RECORD
pddb-0.3.3.dist-info/WHEEL
pddb-0.3.3.dist-info/metadata.json
pddb-0.3.3.dist-info/top_level.txt
