Metadata-Version: 2.0
Name: pddb
Version: 0.3.3
Summary: Prototyping database engine for Python
Home-page: https://github.com/omtinez/pddb
Author: Oscar Martinez
Author-email: omtinez@gmail.com
License: MIT
Keywords: pddb
Platform: UNKNOWN
Classifier: Development Status :: 2 - Pre-Alpha
Classifier: Intended Audience :: Developers
Classifier: License :: OSI Approved :: MIT License
Classifier: Natural Language :: English
Classifier: Programming Language :: Python :: 2
Classifier: Programming Language :: Python :: 2.7
Classifier: Programming Language :: Python :: 3
Classifier: Programming Language :: Python :: 3.3
Classifier: Programming Language :: Python :: 3.4
Classifier: Programming Language :: Python :: 3.5
Requires-Dist: bottle
Requires-Dist: pandas
